[{"design": "F02_verify_smallcase", "pid": "P1", "trial": 0, "answer": "272522"}, {"design": "F02_verify_smallcase", "pid": "P2", "trial": 0, "answer": "5/54"}, {"design": "F02_verify_smallcase", "pid": "P3", "trial": 0, "answer": "blue"}, {"design": "F02_verify_smallcase", "pid": "P4", "trial": 0, "answer": "8418"}, {"design": "F02_verify_smallcase", "pid": "P5", "trial": 0, "answer": "5"}, {"design": "F02_verify_smallcase", "pid": "P6", "trial": 0, "answer": "11/566"}, {"design": "F02_verify_smallcase", "pid": "P7", "trial": 0, "answer": "19"}, {"design": "F02_verify_smallcase", "pid": "P8", "trial": 0, "answer": "5"}, {"design": "F02_verify_smallcase", "pid": "P9", "trial": 0, "answer": "24/5"}, {"design": "F02_verify_smallcase", "pid": "P10", "trial": 0, "answer": "34650"}, {"design": "F02_verify_smallcase", "pid": "P11", "trial": 0, "answer": "26666"}, {"design": "F02_verify_smallcase", "pid": "P12", "trial": 0, "answer": "1/2"}, {"design": "F02_verify_smallcase", "pid": "P13", "trial": 0, "answer": "B"}, {"design": "F02_verify_smallcase", "pid": "P14", "trial": 0, "answer": "256"}, {"design": "F02_verify_smallcase", "pid": "P15", "trial": 0, "answer": "19"}, {"design": "F02_verify_smallcase", "pid": "P16", "trial": 0, "answer": "1/3"}, {"design": "F02_verify_smallcase", "pid": "P17", "trial": 0, "answer": "6"}, {"design": "F02_verify_smallcase", "pid": "P18", "trial": 0, "answer": "5"}, {"design": "F02_verify_smallcase", "pid": "P19", "trial": 0, "answer": "242"}, {"design": "F02_verify_smallcase", "pid": "P20", "trial": 0, "answer": "24"}, {"design": "F02_verify_dual_track", "pid": "P1", "trial": 0, "answer": "272522"}, {"design": "F02_verify_dual_track", "pid": "P2", "trial": 0, "answer": "5/54"}, {"design": "F02_verify_dual_track", "pid": "P3", "trial": 0, "answer": "blue"}, {"design": "F02_verify_dual_track", "pid": "P4", "trial": 0, "answer": "8418"}, {"design": "F02_verify_dual_track", "pid": "P5", "trial": 0, "answer": "5"}, {"design": "F02_verify_dual_track", "pid": "P6", "trial": 0, "answer": "11/566"}, {"design": "F02_verify_dual_track", "pid": "P7", "trial": 0, "answer": "19"}, {"design": "F02_verify_dual_track", "pid": "P8", "trial": 0, "answer": "5"}, {"design": "F02_verify_dual_track", "pid": "P9", "trial": 0, "answer": "24/5"}, {"design": "F02_verify_dual_track", "pid": "P10", "trial": 0, "answer": "34650"}, {"design": "F02_verify_dual_track", "pid": "P11", "trial": 0, "answer": "26666"}, {"design": "F02_verify_dual_track", "pid": "P12", "trial": 0, "answer": "1/2"}, {"design": "F02_verify_dual_track", "pid": "P13", "trial": 0, "answer": "B"}, {"design": "F02_verify_dual_track", "pid": "P14", "trial": 0, "answer": "256"}, {"design": "F02_verify_dual_track", "pid": "P15", "trial": 0, "answer": "19"}, {"design": "F02_verify_dual_track", "pid": "P16", "trial": 0, "answer": "1/3"}, {"design": "F02_verify_dual_track", "pid": "P17", "trial": 0, "answer": "6"}, {"design": "F02_verify_dual_track", "pid": "P18", "trial": 0, "answer": "5"}, {"design": "F02_verify_dual_track", "pid": "P19", "trial": 0, "answer": "242"}, {"design": "F02_verify_dual_track", "pid": "P20", "trial": 0, "answer": "24"}, {"design": "F01_decomp_b", "pid": "P1", "trial": 0, "answer": "272522"}, {"design": "F01_decomp_b", "pid": "P2", "trial": 0, "answer": "5/54"}, {"design": "F01_decomp_b", "pid": "P3", "trial": 0, "answer": "blue"}, {"design": "F01_decomp_b", "pid": "P4", "trial": 0, "answer": "8748"}, {"design": "F01_decomp_b", "pid": "P5", "trial": 0, "answer": "5"}, {"design": "F01_decomp_b", "pid": "P6", "trial": 0, "answer": "11/566"}, {"design": "F01_decomp_b", "pid": "P7", "trial": 0, "answer": "19"}, {"design": "F01_decomp_b", "pid": "P8", "trial": 0, "answer": "5"}, {"design": "F01_decomp_b", "pid": "P9", "trial": 0, "answer": "24/5"}, {"design": "F01_decomp_b", "pid": "P10", "trial": 0, "answer": "34650"}, {"design": "F01_decomp_b", "pid": "P11", "trial": 0, "answer": "26666"}, {"design": "F01_decomp_b", "pid": "P12", "trial": 0, "answer": "1/2"}, {"design": "F01_decomp_b", "pid": "P13", "trial": 0, "answer": "B"}, {"design": "F01_decomp_b", "pid": "P14", "trial": 0, "answer": "256"}, {"design": "F01_decomp_b", "pid": "P15", "trial": 0, "answer": "19"}, {"design": "F01_decomp_b", "pid": "P16", "trial": 0, "answer": "1/3"}, {"design": "F01_decomp_b", "pid": "P17", "trial": 0, "answer": "6"}, {"design": "F01_decomp_b", "pid": "P18", "trial": 0, "answer": "5"}, {"design": "F01_decomp_b", "pid": "P19", "trial": 0, "answer": "242"}, {"design": "F01_decomp_b", "pid": "P20", "trial": 0, "answer": "24"}, {"design": "F02_verify_bayes_table", "pid": "P1", "trial": 0, "answer": "272522"}, {"design": "F02_verify_bayes_table", "pid": "P2", "trial": 0, "answer": "5/54"}, {"design": "F02_verify_bayes_table", "pid": "P3", "trial": 0, "answer": "blue"}, {"design": "F02_verify_bayes_table", "pid": "P4", "trial": 0, "answer": "8418"}, {"design": "F02_verify_bayes_table", "pid": "P5", "trial": 0, "answer": "5"}, {"design": "F02_verify_bayes_table", "pid": "P6", "trial": 0, "answer": "11/566"}, {"design": "F02_verify_bayes_table", "pid": "P7", "trial": 0, "answer": "19"}, {"design": "F02_verify_bayes_table", "pid": "P8", "trial": 0, "answer": "5"}, {"design": "F02_verify_bayes_table", "pid": "P9", "trial": 0, "answer": "24/5"}, {"design": "F02_verify_bayes_table", "pid": "P10", "trial": 0, "answer": "34650"}, {"design": "F02_verify_bayes_table", "pid": "P11", "trial": 0, "answer": "26666"}, {"design": "F02_verify_bayes_table", "pid": "P12", "trial": 0, "answer": "1/2"}, {"design": "F02_verify_bayes_table", "pid": "P13", "trial": 0, "answer": "B"}, {"design": "F02_verify_bayes_table", "pid": "P14", "trial": 0, "answer": "256"}, {"design": "F02_verify_bayes_table", "pid": "P15", "trial": 0, "answer": "19"}, {"design": "F02_verify_bayes_table", "pid": "P16", "trial": 0, "answer": "1/3"}, {"design": "F02_verify_bayes_table", "pid": "P17", "trial": 0, "answer": "6"}, {"design": "F02_verify_bayes_table", "pid": "P18", "trial": 0, "answer": "8"}, {"design": "F02_verify_bayes_table", "pid": "P19", "trial": 0, "answer": "242"}, {"design": "F02_verify_bayes_table", "pid": "P20", "trial": 0, "answer": "24"}, {"design": "F11_metacog_b", "pid": "P1", "trial": 0, "answer": "272522"}, {"design": "F11_metacog_b", "pid": "P2", "trial": 0, "answer": "5/54"}, {"design": "F11_metacog_b", "pid": "P3", "trial": 0, "answer": "blue"}, {"design": "F11_metacog_b", "pid": "P4", "trial": 0, "answer": "8417"}, {"design": "F11_metacog_b", "pid": "P5", "trial": 0, "answer": "5"}, {"design": "F11_metacog_b", "pid": "P6", "trial": 0, "answer": "11/566"}, {"design": "F11_metacog_b", "pid": "P7", "trial": 0, "answer": "19"}, {"design": "F11_metacog_b", "pid": "P8", "trial": 0, "answer": "5"}, {"design": "F11_metacog_b", "pid": "P9", "trial": 0, "answer": "24/5"}, {"design": "F11_metacog_b", "pid": "P10", "trial": 0, "answer": "34650"}, {"design": "F11_metacog_b", "pid": "P11", "trial": 0, "answer": "26666"}, {"design": "F11_metacog_b", "pid": "P12", "trial": 0, "answer": "1/2"}, {"design": "F11_metacog_b", "pid": "P13", "trial": 0, "answer": "B"}, {"design": "F11_metacog_b", "pid": "P14", "trial": 0, "answer": "256"}, {"design": "F11_metacog_b", "pid": "P15", "trial": 0, "answer": "19"}, {"design": "F11_metacog_b", "pid": "P16", "trial": 0, "answer": "1/3"}, {"design": "F11_metacog_b", "pid": "P17", "trial": 0, "answer": "6"}, {"design": "F11_metacog_b", "pid": "P18", "trial": 0, "answer": "5"}, {"design": "F11_metacog_b", "pid": "P19", "trial": 0, "answer": "242"}, {"design": "F11_metacog_b", "pid": "P20", "trial": 0, "answer": "24"}, {"design": "F01_decomp_c", "pid": "P1", "trial": 0, "answer": "272522"}, {"design": "F01_decomp_c", "pid": "P2", "trial": 0, "answer": "5/54"}, {"design": "F01_decomp_c", "pid": "P3", "trial": 0, "answer": "blue"}, {"design": "F01_decomp_c", "pid": "P4", "trial": 0, "answer": "8938"}, {"design": "F01_decomp_c", "pid": "P5", "trial": 0, "answer": "5"}, {"design": "F01_decomp_c", "pid": "P6", "trial": 0, "answer": "11/566"}, {"design": "F01_decomp_c", "pid": "P7", "trial": 0, "answer": "19"}, {"design": "F01_decomp_c", "pid": "P8", "trial": 0, "answer": "5"}, {"design": "F01_decomp_c", "pid": "P9", "trial": 0, "answer": "24/5"}, {"design": "F01_decomp_c", "pid": "P10", "trial": 0, "answer": "34650"}, {"design": "F01_decomp_c", "pid": "P11", "trial": 0, "answer": "26666"}, {"design": "F01_decomp_c", "pid": "P12", "trial": 0, "answer": "1/2"}, {"design": "F01_decomp_c", "pid": "P13", "trial": 0, "answer": "B"}, {"design": "F01_decomp_c", "pid": "P14", "trial": 0, "answer": "256"}, {"design": "F01_decomp_c", "pid": "P15", "trial": 0, "answer": "19"}, {"design": "F01_decomp_c", "pid": "P16", "trial": 0, "answer": "1/3"}, {"design": "F01_decomp_c", "pid": "P17", "trial": 0, "answer": "6"}, {"design": "F01_decomp_c", "pid": "P18", "trial": 0, "answer": "5"}, {"design": "F01_decomp_c", "pid": "P19", "trial": 0, "answer": "242"}, {"design": "F01_decomp_c", "pid": "P20", "trial": 0, "answer": "24"}, {"design": "F01_decomp_h", "pid": "P1", "trial": 0, "answer": "276333"}, {"design": "F01_decomp_h", "pid": "P2", "trial": 0, "answer": "5/54"}, {"design": "F01_decomp_h", "pid": "P3", "trial": 0, "answer": "blue"}, {"design": "F01_decomp_h", "pid": "P4", "trial": 0, "answer": "8418"}, {"design": "F01_decomp_h", "pid": "P5", "trial": 0, "answer": "5"}, {"design": "F01_decomp_h", "pid": "P6", "trial": 0, "answer": "11/566"}, {"design": "F01_decomp_h", "pid": "P7", "trial": 0, "answer": "19"}, {"design": "F01_decomp_h", "pid": "P8", "trial": 0, "answer": "5"}, {"design": "F01_decomp_h", "pid": "P9", "trial": 0, "answer": "24/5"}, {"design": "F01_decomp_h", "pid": "P10", "trial": 0, "answer": "34650"}, {"design": "F01_decomp_h", "pid": "P11", "trial": 0, "answer": "26666"}, {"design": "F01_decomp_h", "pid": "P12", "trial": 0, "answer": "1/2"}, {"design": "F01_decomp_h", "pid": "P13", "trial": 0, "answer": "B"}, {"design": "F01_decomp_h", "pid": "P14", "trial": 0, "answer": "256"}, {"design": "F01_decomp_h", "pid": "P15", "trial": 0, "answer": "19"}, {"design": "F01_decomp_h", "pid": "P16", "trial": 0, "answer": "1/3"}, {"design": "F01_decomp_h", "pid": "P17", "trial": 0, "answer": "6"}, {"design": "F01_decomp_h", "pid": "P18", "trial": 0, "answer": "5"}, {"design": "F01_decomp_h", "pid": "P19", "trial": 0, "answer": "242"}, {"design": "F01_decomp_h", "pid": "P20", "trial": 0, "answer": "24"}, {"design": "F02_verify_three_vote", "pid": "P1", "trial": 0, "answer": "272522"}, {"design": "F02_verify_three_vote", "pid": "P2", "trial": 0, "answer": "5/54"}, {"design": "F02_verify_three_vote", "pid": "P3", "trial": 0, "answer": "blue"}, {"design": "F02_verify_three_vote", "pid": "P4", "trial": 0, "answer": "8424"}, {"design": "F02_verify_three_vote", "pid": "P5", "trial": 0, "answer": "5"}, {"design": "F02_verify_three_vote", "pid": "P6", "trial": 0, "answer": "11/566"}, {"design": "F02_verify_three_vote", "pid": "P7", "trial": 0, "answer": "19"}, {"design": "F02_verify_three_vote", "pid": "P8", "trial": 0, "answer": "5"}, {"design": "F02_verify_three_vote", "pid": "P9", "trial": 0, "answer": "24/5"}, {"design": "F02_verify_three_vote", "pid": "P10", "trial": 0, "answer": "34650"}, {"design": "F02_verify_three_vote", "pid": "P11", "trial": 0, "answer": "26666"}, {"design": "F02_verify_three_vote", "pid": "P12", "trial": 0, "answer": "1/2"}, {"design": "F02_verify_three_vote", "pid": "P13", "trial": 0, "answer": "B"}, {"design": "F02_verify_three_vote", "pid": "P14", "trial": 0, "answer": "256"}, {"design": "F02_verify_three_vote", "pid": "P15", "trial": 0, "answer": "19"}, {"design": "F02_verify_three_vote", "pid": "P16", "trial": 0, "answer": "1/3"}, {"design": "F02_verify_three_vote", "pid": "P17", "trial": 0, "answer": "6"}, {"design": "F02_verify_three_vote", "pid": "P18", "trial": 0, "answer": "5"}, {"design": "F02_verify_three_vote", "pid": "P19", "trial": 0, "answer": "242"}, {"design": "F02_verify_three_vote", "pid": "P20", "trial": 0, "answer": "24"}, {"design": "F01_decomp_d", "pid": "P1", "trial": 0, "answer": "272522"}, {"design": "F01_decomp_d", "pid": "P2", "trial": 0, "answer": "5/54"}, {"design": "F01_decomp_d", "pid": "P3", "trial": 0, "answer": "blue"}, {"design": "F01_decomp_d", "pid": "P4", "trial": 0, "answer": "8418"}, {"design": "F01_decomp_d", "pid": "P5", "trial": 0, "answer": "5"}, {"design": "F01_decomp_d", "pid": "P6", "trial": 0, "answer": "11/566"}, {"design": "F01_decomp_d", "pid": "P7", "trial": 0, "answer": "19"}, {"design": "F01_decomp_d", "pid": "P8", "trial": 0, "answer": "5"}, {"design": "F01_decomp_d", "pid": "P9", "trial": 0, "answer": "24/5"}, {"design": "F01_decomp_d", "pid": "P10", "trial": 0, "answer": "34650"}, {"design": "F01_decomp_d", "pid": "P11", "trial": 0, "answer": "26666"}, {"design": "F01_decomp_d", "pid": "P12", "trial": 0, "answer": "1/2"}, {"design": "F01_decomp_d", "pid": "P13", "trial": 0, "answer": "B"}, {"design": "F01_decomp_d", "pid": "P14", "trial": 0, "answer": "256"}, {"design": "F01_decomp_d", "pid": "P15", "trial": 0, "answer": "19"}, {"design": "F01_decomp_d", "pid": "P16", "trial": 0, "answer": "1/3"}, {"design": "F01_decomp_d", "pid": "P17", "trial": 0, "answer": "6"}, {"design": "F01_decomp_d", "pid": "P18", "trial": 0, "answer": "8"}, {"design": "F01_decomp_d", "pid": "P19", "trial": 0, "answer": "242"}, {"design": "F01_decomp_d", "pid": "P20", "trial": 0, "answer": "24"}, {"design": "F03_adversarial_c", "pid": "P1", "trial": 0, "answer": "272522"}, {"design": "F03_adversarial_c", "pid": "P2", "trial": 0, "answer": "5/54"}, {"design": "F03_adversarial_c", "pid": "P3", "trial": 0, "answer": "blue"}, {"design": "F03_adversarial_c", "pid": "P4", "trial": 0, "answer": "8418"}, {"design": "F03_adversarial_c", "pid": "P5", "trial": 0, "answer": "5"}, {"design": "F03_adversarial_c", "pid": "P6", "trial": 0, "answer": "11/566"}, {"design": "F03_adversarial_c", "pid": "P7", "trial": 0, "answer": "19"}, {"design": "F03_adversarial_c", "pid": "P8", "trial": 0, "answer": "5"}, {"design": "F03_adversarial_c", "pid": "P9", "trial": 0, "answer": "24/5"}, {"design": "F03_adversarial_c", "pid": "P10", "trial": 0, "answer": "34650"}, {"design": "F03_adversarial_c", "pid": "P11", "trial": 0, "answer": "26666"}, {"design": "F03_adversarial_c", "pid": "P12", "trial": 0, "answer": "1/2"}, {"design": "F03_adversarial_c", "pid": "P13", "trial": 0, "answer": "B"}, {"design": "F03_adversarial_c", "pid": "P14", "trial": 0, "answer": "256"}, {"design": "F03_adversarial_c", "pid": "P15", "trial": 0, "answer": "19"}, {"design": "F03_adversarial_c", "pid": "P16", "trial": 0, "answer": "1/3"}, {"design": "F03_adversarial_c", "pid": "P17", "trial": 0, "answer": "6"}, {"design": "F03_adversarial_c", "pid": "P18", "trial": 0, "answer": "5"}, {"design": "F03_adversarial_c", "pid": "P19", "trial": 0, "answer": "242"}, {"design": "F03_adversarial_c", "pid": "P20", "trial": 0, "answer": "24"}, {"design": "C0_baseline", "pid": "P1", "trial": 0, "answer": "272522"}, {"design": "C0_baseline", "pid": "P2", "trial": 0, "answer": "5/54"}, {"design": "C0_baseline", "pid": "P3", "trial": 0, "answer": "blue"}, {"design": "C0_baseline", "pid": "P4", "trial": 0, "answer": "8938"}, {"design": "C0_baseline", "pid": "P5", "trial": 0, "answer": "5"}, {"design": "C0_baseline", "pid": "P6", "trial": 0, "answer": "11/566"}, {"design": "C0_baseline", "pid": "P7", "trial": 0, "answer": "19"}, {"design": "C0_baseline", "pid": "P8", "trial": 0, "answer": "5"}, {"design": "C0_baseline", "pid": "P9", "trial": 0, "answer": "24/5"}, {"design": "C0_baseline", "pid": "P10", "trial": 0, "answer": "34650"}, {"design": "C0_baseline", "pid": "P11", "trial": 0, "answer": "26666"}, {"design": "C0_baseline", "pid": "P12", "trial": 0, "answer": "1/2"}, {"design": "C0_baseline", "pid": "P13", "trial": 0, "answer": "B"}, {"design": "C0_baseline", "pid": "P14", "trial": 0, "answer": "256"}, {"design": "C0_baseline", "pid": "P15", "trial": 0, "answer": "19"}, {"design": "C0_baseline", "pid": "P16", "trial": 0, "answer": "1/3"}, {"design": "C0_baseline", "pid": "P17", "trial": 0, "answer": "6"}, {"design": "C0_baseline", "pid": "P18", "trial": 0, "answer": "5"}, {"design": "C0_baseline", "pid": "P19", "trial": 0, "answer": "242"}, {"design": "C0_baseline", "pid": "P20", "trial": 0, "answer": "24"}, {"design": "C2_selfverify", "pid": "P1", "trial": 0, "answer": "272522"}, {"design": "C2_selfverify", "pid": "P2", "trial": 0, "answer": "5/54"}, {"design": "C2_selfverify", "pid": "P3", "trial": 0, "answer": "blue"}, {"design": "C2_selfverify", "pid": "P4", "trial": 0, "answer": "8418"}, {"design": "C2_selfverify", "pid": "P5", "trial": 0, "answer": "5"}, {"design": "C2_selfverify", "pid": "P6", "trial": 0, "answer": "11/566"}, {"design": "C2_selfverify", "pid": "P7", "trial": 0, "answer": "19"}, {"design": "C2_selfverify", "pid": "P8", "trial": 0, "answer": "5"}, {"design": "C2_selfverify", "pid": "P9", "trial": 0, "answer": "24/5"}, {"design": "C2_selfverify", "pid": "P10", "trial": 0, "answer": "34650"}, {"design": "C2_selfverify", "pid": "P11", "trial": 0, "answer": "26666"}, {"design": "C2_selfverify", "pid": "P12", "trial": 0, "answer": "1/2"}, {"design": "C2_selfverify", "pid": "P13", "trial": 0, "answer": "B"}, {"design": "C2_selfverify", "pid": "P14", "trial": 0, "answer": "256"}, {"design": "C2_selfverify", "pid": "P15", "trial": 0, "answer": "19"}, {"design": "C2_selfverify", "pid": "P16", "trial": 0, "answer": "1/3"}, {"design": "C2_selfverify", "pid": "P17", "trial": 0, "answer": "6"}, {"design": "C2_selfverify", "pid": "P18", "trial": 0, "answer": "5"}, {"design": "C2_selfverify", "pid": "P19", "trial": 0, "answer": "242"}, {"design": "C2_selfverify", "pid": "P20", "trial": 0, "answer": "24"}]